eddy/__init__.py
eddy/__main__.py
eddy/core/__init__.py
eddy/core/application.py
eddy/core/clipboard.py
eddy/core/commandline.py
eddy/core/common.py
eddy/core/diagram.py
eddy/core/factory.py
eddy/core/generators.py
eddy/core/ndc.py
eddy/core/network.py
eddy/core/output.py
eddy/core/owl.py
eddy/core/plugin.py
eddy/core/project.py
eddy/core/qt.py
eddy/core/regex.py
eddy/core/sparql.py
eddy/core/timer.py
eddy/core/worker.py
eddy/core/commands/__init__.py
eddy/core/commands/common.py
eddy/core/commands/diagram.py
eddy/core/commands/edges.py
eddy/core/commands/iri.py
eddy/core/commands/labels.py
eddy/core/commands/nodes.py
eddy/core/commands/project.py
eddy/core/datatypes/__init__.py
eddy/core/datatypes/collections.py
eddy/core/datatypes/common.py
eddy/core/datatypes/graphol.py
eddy/core/datatypes/misc.py
eddy/core/datatypes/owl.py
eddy/core/datatypes/qt.py
eddy/core/datatypes/system.py
eddy/core/exporters/__init__.py
eddy/core/exporters/common.py
eddy/core/exporters/graphml.py
eddy/core/exporters/graphol.py
eddy/core/exporters/graphol_iri.py
eddy/core/exporters/graphreferences.py
eddy/core/exporters/image.py
eddy/core/exporters/metadata.py
eddy/core/exporters/owl2.py
eddy/core/exporters/pdf.py
eddy/core/exporters/printer.py
eddy/core/functions/__init__.py
eddy/core/functions/fsystem.py
eddy/core/functions/geometry.py
eddy/core/functions/graph.py
eddy/core/functions/misc.py
eddy/core/functions/owl.py
eddy/core/functions/path.py
eddy/core/functions/signals.py
eddy/core/items/__init__.py
eddy/core/items/common.py
eddy/core/items/factory.py
eddy/core/items/edges/__init__.py
eddy/core/items/edges/different.py
eddy/core/items/edges/equivalence.py
eddy/core/items/edges/inclusion.py
eddy/core/items/edges/input.py
eddy/core/items/edges/membership.py
eddy/core/items/edges/same.py
eddy/core/items/edges/common/__init__.py
eddy/core/items/edges/common/base.py
eddy/core/items/edges/common/label.py
eddy/core/items/nodes/__init__.py
eddy/core/items/nodes/attribute.py
eddy-3.8.dist-info/licenses/LICENSE
eddy-3.8.dist-info/METADATA
eddy-3.8.dist-info/WHEEL
eddy-3.8.dist-info/entry_points.txt
eddy-3.8.dist-info/top_level.txt
eddy-3.8.dist-info/RECORD
