Metadata-Version: 2.4
Name: Eddy
Version: 3.8
Summary: Eddy is a graphical editor for the specification and visualization of Graphol ontologies.
Home-page: https://github.com/obdasystems/eddy
Author: Daniele Pantaleone
Author-email: pantaleone@dis.uniroma1.it
Maintainer: Manuel Namici
Maintainer-email: namici@diag.uniroma1.it
License: GPL-3.0-or-later
Keywords: eddy graphol sapienza
Classifier: Development Status :: 5 - Production/Stable
Classifier: Environment :: MacOS X :: Cocoa
Classifier: Environment :: Win32 (MS Windows)
Classifier: Environment :: X11 Applications :: Qt
Classifier: Intended Audience :: Science/Research
Classifier: Natural Language :: English
Classifier: Operating System :: MacOS
Classifier: Operating System :: Microsoft :: Windows
Classifier: Operating System :: POSIX :: BSD
Classifier: Operating System :: POSIX :: Linux
Classifier: Programming Language :: Python :: 3
Classifier: Programming Language :: Python :: 3.10
Classifier: Programming Language :: Python :: 3.11
Classifier: Programming Language :: Python :: 3.12
Classifier: Programming Language :: Python :: 3.13
Classifier: Programming Language :: Python :: 3.14
Classifier: Topic :: Scientific/Engineering :: Artificial Intelligence
Classifier: Topic :: Utilities
Requires-Python: >=3.10
License-File: LICENSE
Requires-Dist: jpype1>=1.4.1
Requires-Dist: rdflib>=6.2.0
Requires-Dist: rfc3987
Requires-Dist: openpyxl
Dynamic: author
Dynamic: author-email
Dynamic: classifier
Dynamic: description
Dynamic: description-content-type
Dynamic: home-page
Dynamic: keywords
Dynamic: license
Dynamic: license-file
Dynamic: maintainer
Dynamic: maintainer-email
Dynamic: requires-dist
Dynamic: requires-python
Dynamic: summary
